{
  "wer": 0.1484848484848485,
  "insertions": 29,
  "deletions": 6,
  "substitutions": 14,
  "mismatches": [
    {
      "operation": "insert",
      "index_ref": 54,
      "index_hyp": 54,
      "ref_word": "",
      "hyp_word": "stylecast",
      "ref_context": "",
      "hyp_context": "to fetch your products your stylecast x revolt men opaque casual"
    },
    {
      "operation": "insert",
      "index_ref": 54,
      "index_hyp": 55,
      "ref_word": "",
      "hyp_word": "x",
      "ref_context": "",
      "hyp_context": "fetch your products your stylecast x revolt men opaque casual shirt"
    },
    {
      "operation": "insert",
      "index_ref": 54,
      "index_hyp": 56,
      "ref_word": "",
      "hyp_word": "revolt",
      "ref_context": "",
      "hyp_context": "your products your stylecast x revolt men opaque casual shirt is"
    },
    {
      "operation": "insert",
      "index_ref": 54,
      "index_hyp": 57,
      "ref_word": "",
      "hyp_word": "men",
      "ref_context": "",
      "hyp_context": "products your stylecast x revolt men opaque casual shirt is being"
    },
    {
      "operation": "insert",
      "index_ref": 54,
      "index_hyp": 58,
      "ref_word": "",
      "hyp_word": "opaque",
      "ref_context": "",
      "hyp_context": "your stylecast x revolt men opaque casual shirt is being processed"
    },
    {
      "operation": "insert",
      "index_ref": 54,
      "index_hyp": 59,
      "ref_word": "",
      "hyp_word": "casual",
      "ref_context": "",
      "hyp_context": "stylecast x revolt men opaque casual shirt is being processed and"
    },
    {
      "operation": "insert",
      "index_ref": 54,
      "index_hyp": 60,
      "ref_word": "",
      "hyp_word": "shirt",
      "ref_context": "",
      "hyp_context": "x revolt men opaque casual shirt is being processed and will"
    },
    {
      "operation": "insert",
      "index_ref": 54,
      "index_hyp": 61,
      "ref_word": "",
      "hyp_word": "is",
      "ref_context": "",
      "hyp_context": "revolt men opaque casual shirt is being processed and will be"
    },
    {
      "operation": "insert",
      "index_ref": 54,
      "index_hyp": 62,
      "ref_word": "",
      "hyp_word": "being",
      "ref_context": "",
      "hyp_context": "men opaque casual shirt is being processed and will be delivered"
    },
    {
      "operation": "insert",
      "index_ref": 54,
      "index_hyp": 63,
      "ref_word": "",
      "hyp_word": "processed",
      "ref_context": "",
      "hyp_context": "opaque casual shirt is being processed and will be delivered by"
    },
    {
      "operation": "insert",
      "index_ref": 54,
      "index_hyp": 64,
      "ref_word": "",
      "hyp_word": "and",
      "ref_context": "",
      "hyp_context": "casual shirt is being processed and will be delivered by 21"
    },
    {
      "operation": "insert",
      "index_ref": 54,
      "index_hyp": 65,
      "ref_word": "",
      "hyp_word": "will",
      "ref_context": "",
      "hyp_context": "shirt is being processed and will be delivered by 21 august"
    },
    {
      "operation": "insert",
      "index_ref": 54,
      "index_hyp": 66,
      "ref_word": "",
      "hyp_word": "be",
      "ref_context": "",
      "hyp_context": "is being processed and will be delivered by 21 august please"
    },
    {
      "operation": "insert",
      "index_ref": 54,
      "index_hyp": 67,
      "ref_word": "",
      "hyp_word": "delivered",
      "ref_context": "",
      "hyp_context": "being processed and will be delivered by 21 august please tell"
    },
    {
      "operation": "insert",
      "index_ref": 54,
      "index_hyp": 68,
      "ref_word": "",
      "hyp_word": "by",
      "ref_context": "",
      "hyp_context": "processed and will be delivered by 21 august please tell me"
    },
    {
      "operation": "insert",
      "index_ref": 54,
      "index_hyp": 69,
      "ref_word": "",
      "hyp_word": "21",
      "ref_context": "",
      "hyp_context": "and will be delivered by 21 august please tell me is"
    },
    {
      "operation": "insert",
      "index_ref": 54,
      "index_hyp": 70,
      "ref_word": "",
      "hyp_word": "august",
      "ref_context": "",
      "hyp_context": "will be delivered by 21 august please tell me is there"
    },
    {
      "operation": "insert",
      "index_ref": 54,
      "index_hyp": 71,
      "ref_word": "",
      "hyp_word": "please",
      "ref_context": "",
      "hyp_context": "be delivered by 21 august please tell me is there anything"
    },
    {
      "operation": "insert",
      "index_ref": 54,
      "index_hyp": 72,
      "ref_word": "",
      "hyp_word": "tell",
      "ref_context": "",
      "hyp_context": "delivered by 21 august please tell me is there anything else"
    },
    {
      "operation": "insert",
      "index_ref": 54,
      "index_hyp": 73,
      "ref_word": "",
      "hyp_word": "me",
      "ref_context": "",
      "hyp_context": "by 21 august please tell me is there anything else i"
    },
    {
      "operation": "insert",
      "index_ref": 54,
      "index_hyp": 74,
      "ref_word": "",
      "hyp_word": "is",
      "ref_context": "",
      "hyp_context": "21 august please tell me is there anything else i can"
    },
    {
      "operation": "insert",
      "index_ref": 54,
      "index_hyp": 75,
      "ref_word": "",
      "hyp_word": "there",
      "ref_context": "",
      "hyp_context": "august please tell me is there anything else i can help"
    },
    {
      "operation": "insert",
      "index_ref": 54,
      "index_hyp": 76,
      "ref_word": "",
      "hyp_word": "anything",
      "ref_context": "",
      "hyp_context": "please tell me is there anything else i can help you"
    },
    {
      "operation": "insert",
      "index_ref": 54,
      "index_hyp": 77,
      "ref_word": "",
      "hyp_word": "else",
      "ref_context": "",
      "hyp_context": "tell me is there anything else i can help you with"
    },
    {
      "operation": "insert",
      "index_ref": 54,
      "index_hyp": 78,
      "ref_word": "",
      "hyp_word": "i",
      "ref_context": "",
      "hyp_context": "me is there anything else i can help you with sure"
    },
    {
      "operation": "insert",
      "index_ref": 54,
      "index_hyp": 79,
      "ref_word": "",
      "hyp_word": "can",
      "ref_context": "",
      "hyp_context": "is there anything else i can help you with sure how"
    },
    {
      "operation": "insert",
      "index_ref": 54,
      "index_hyp": 80,
      "ref_word": "",
      "hyp_word": "help",
      "ref_context": "",
      "hyp_context": "there anything else i can help you with sure how else"
    },
    {
      "operation": "insert",
      "index_ref": 54,
      "index_hyp": 81,
      "ref_word": "",
      "hyp_word": "you",
      "ref_context": "",
      "hyp_context": "anything else i can help you with sure how else can"
    },
    {
      "operation": "replace",
      "index_ref": 54,
      "index_hyp": 82,
      "ref_word": "style",
      "hyp_word": "with",
      "ref_context": "to fetch your products your style sure how else can i",
      "hyp_context": "else i can help you with sure how else can i"
    },
    {
      "operation": "replace",
      "index_ref": 92,
      "index_hyp": 120,
      "ref_word": "our",
      "hyp_word": "your",
      "ref_context": "me repeat that for you our style cast x revolt men",
      "hyp_context": "me repeat that for you your stylecast x revolt men opaque"
    },
    {
      "operation": "replace",
      "index_ref": 93,
      "index_hyp": 121,
      "ref_word": "style",
      "hyp_word": "stylecast",
      "ref_context": "repeat that for you our style cast x revolt men opaque",
      "hyp_context": "repeat that for you your stylecast x revolt men opaque casual"
    },
    {
      "operation": "delete",
      "index_ref": 94,
      "index_hyp": 122,
      "ref_word": "cast",
      "hyp_word": "",
      "ref_context": "that for you our style cast x revolt men opaque casual",
      "hyp_context": ""
    },
    {
      "operation": "replace",
      "index_ref": 106,
      "index_hyp": 133,
      "ref_word": "21st",
      "hyp_word": "21",
      "ref_context": "is scheduled for delivery by 21st august let me know if",
      "hyp_context": "is scheduled for delivery by 21 august let me know if"
    },
    {
      "operation": "replace",
      "index_ref": 148,
      "index_hyp": 175,
      "ref_word": "all",
      "hyp_word": "alright",
      "ref_context": "quiet are you still there all right please let me know",
      "hyp_context": "quiet are you still there alright please let me know how"
    },
    {
      "operation": "delete",
      "index_ref": 149,
      "index_hyp": 176,
      "ref_word": "right",
      "hyp_word": "",
      "ref_context": "are you still there all right please let me know how",
      "hyp_context": ""
    },
    {
      "operation": "delete",
      "index_ref": 166,
      "index_hyp": 192,
      "ref_word": "city",
      "hyp_word": "",
      "ref_context": "is out for delivery the city the delivery partner will call",
      "hyp_context": ""
    },
    {
      "operation": "delete",
      "index_ref": 167,
      "index_hyp": 192,
      "ref_word": "the",
      "hyp_word": "",
      "ref_context": "out for delivery the city the delivery partner will call you",
      "hyp_context": ""
    },
    {
      "operation": "replace",
      "index_ref": 214,
      "index_hyp": 238,
      "ref_word": "order",
      "hyp_word": "orders",
      "ref_context": "app by going to the order section selecting the item and",
      "hyp_context": "app by going to the orders section selecting the item and"
    },
    {
      "operation": "replace",
      "index_ref": 252,
      "index_hyp": 276,
      "ref_word": "order",
      "hyp_word": "orders",
      "ref_context": "the app go to the order section select currently exchanges can",
      "hyp_context": "the app go to the orders section select the currently exchanges"
    },
    {
      "operation": "insert",
      "index_ref": 255,
      "index_hyp": 279,
      "ref_word": "",
      "hyp_word": "the",
      "ref_context": "",
      "hyp_context": "to the orders section select the currently exchanges can only be"
    },
    {
      "operation": "replace",
      "index_ref": 286,
      "index_hyp": 311,
      "ref_word": "delivery",
      "hyp_word": "deliveryrelated",
      "ref_context": "track your orders assist with delivery related queries and provide information",
      "hyp_context": "track your orders assist with deliveryrelated queries and provide information about"
    },
    {
      "operation": "delete",
      "index_ref": 287,
      "index_hyp": 312,
      "ref_word": "related",
      "hyp_word": "",
      "ref_context": "your orders assist with delivery related queries and provide information about",
      "hyp_context": ""
    },
    {
      "operation": "replace",
      "index_ref": 313,
      "index_hyp": 337,
      "ref_word": "sms",
      "hyp_word": "smsyour",
      "ref_context": "a quick feedback form via sms your input would really help",
      "hyp_context": "a quick feedback form via smsyour input would really help us"
    },
    {
      "operation": "delete",
      "index_ref": 314,
      "index_hyp": 338,
      "ref_word": "your",
      "hyp_word": "",
      "ref_context": "quick feedback form via sms your input would really help us",
      "hyp_context": ""
    }
  ],
  "substitution_pairs": [
    {
      "reference": "style",
      "hypothesis": "with"
    },
    {
      "reference": "our",
      "hypothesis": "your"
    },
    {
      "reference": "style",
      "hypothesis": "stylecast"
    },
    {
      "reference": "21st",
      "hypothesis": "21"
    },
    {
      "reference": "all",
      "hypothesis": "alright"
    },
    {
      "reference": "order",
      "hypothesis": "orders"
    },
    {
      "reference": "order",
      "hypothesis": "orders"
    },
    {
      "reference": "delivery",
      "hypothesis": "deliveryrelated"
    },
    {
      "reference": "sms",
      "hypothesis": "smsyour"
    }
  ],
  "deletion_words": [
    "cast",
    "right",
    "city",
    "the",
    "related",
    "your"
  ],
  "insertion_words": [
    "stylecast",
    "x",
    "revolt",
    "men",
    "opaque",
    "casual",
    "shirt",
    "is",
    "being",
    "processed",
    "and",
    "will",
    "be",
    "delivered",
    "by",
    "21",
    "august",
    "please",
    "tell",
    "me",
    "is",
    "there",
    "anything",
    "else",
    "i",
    "can",
    "help",
    "you",
    "the"
  ]
}